pytonb/__init__.py
pytonb/_converter.py
pytonb-1.0.1.dist-info/METADATA
pytonb-1.0.1.dist-info/WHEEL
pytonb-1.0.1.dist-info/licenses/LICENSE
pytonb-1.0.1.dist-info/RECORD
