Metadata-Version: 2.4
Name: pytonb
Version: 1.0.1
Summary: simple converter py<->notebook with sync function
License-File: LICENSE
Requires-Python: >=3.13
